Metadata-Version: 1.0
Name: ihs-probability
Version: 0.1
Summary: Gaussian and Binomial distributions
Home-page: UNKNOWN
Author: Honoré Mbaya
Author-email: honormbaya@gmail.com
License: UNKNOWN
Platform: UNKNOWN
